{
  "users": [
    {
      "username": "moti.vationalquotes675",
      "email": "nehansh100502@gmail.com",
      "password": "snsd",
      "id": "oS5VdqbsH90"
    },
    {
      "username": "moti.vationalquotes675",
      "email": "nehansh100502@gmail.com",
      "password": "snsd",
      "id": "KxXuF49d1XI"
    },
    {
      "username": "moti.vationalquotes675",
      "email": "nehansh100502@gmail.com",
      "password": "snsd",
      "id": "tM5ivoz2tw4"
    },
    {
      "username": "e1072258629",
      "email": "nehansh100502@gmail.com",
      "password": "ddddd.      sssssss sss",
      "id": "lQefVT5e4bc"
    }
  ],
  "$schema": "./node_modules/json-server/schema.json"
}